{
  "config": {
    "whatsappNumero": "554299039243"
  },
  "produtos": [
    {
      "id": "p1",
      "nome": "Porta Maternidade",
      "descricao": "Porta Maternidade Personalizado em Crochê 🌸👶\n\nUma peça única e delicada, feita à mão para tornar a chegada do seu bebê ainda mais especial. Personalizado com o nome da criança e detalhes florais encantadores.\n\n✨ Detalhes do produto:\n\nConfeccionado artesanalmente em crochê.\n\nProduzido com fio Amigurumi Círculo de alta qualidade.\n\nNome personalizado com acabamento delicado e elegante.\n\nFlores aplicadas com detalhes em pérolas e folhas em crochê.\n\nEstrutura leve e resistente, pronta para pendurar.\n\nDecoração exclusiva para quarto de bebê e maternidade.\n\n\n🎀 Ideal para:\n\nEnfeitar a porta da maternidade.\n\nDecorar o quartinho do bebê.\n\nPresentear futuras mamães.\n\nEnsaios fotográficos e chá de bebê.\n\nGuardar como lembrança especial para toda a vida.\n\n\n💝 Produto 100% artesanal, confeccionado com muito amor e atenção aos detalhes. Cada peça é única e pode ser personalizada com nome, cores e tema de sua preferência.\n\n📏 Personalização disponível: escolha o nome, as cores e os detalhes que mais combinam com o seu sonho. 🌷👶✨",
      "preco": 100,
      "categoria": "Crochê",
      "imagem": "images/6980d8d1-a725-4903-8749-519db7363d4a.jpg",
      "destaque": false,
      "criadoEm": "2026-05-30T02:40:24.000Z"
    },
    {
      "id": "p7",
      "nome": "Amiguri LU e DRESA",
      "descricao": "",
      "preco": 34,
      "categoria": "Crochê",
      "imagem": "images/p7-amiguri-lu-dresa.jpg",
      "destaque": false,
      "criadoEm": "2026-05-30T02:40:24.000Z"
    },
    {
      "id": "p8",
      "nome": "Kit Estrela Tapete",
      "descricao": "Feito com linhos retirados do monte guine com todo carinho.",
      "preco": 234.34,
      "categoria": "Crochê",
      "imagem": "images/p8-kit-estrela-tapete.jpg",
      "destaque": false,
      "criadoEm": "2026-05-30T02:40:24.000Z"
    },
    {
      "id": "p9",
      "nome": "Kit LUA Crochê",
      "descricao": "Feito sob medida",
      "preco": 170,
      "categoria": "Crochê",
      "imagem": "images/p9-kit-lua-croche.jpg",
      "destaque": false,
      "criadoEm": "2026-05-30T02:40:24.000Z"
    },
    {
      "id": "p11",
      "nome": "Manga Crochê Mingua",
      "descricao": "manga para quem está com frio quentinho",
      "preco": 70,
      "categoria": "Crochê",
      "imagem": "images/p11-manga-croche.jpg",
      "destaque": false,
      "criadoEm": "2026-05-30T02:40:24.000Z"
    },
    {
      "id": "p12",
      "nome": "Kit Porta Copo Crochê",
      "descricao": "Kit feito com muito carinho",
      "preco": 500,
      "categoria": "Crochê",
      "imagem": "images/p12-porta-copo.jpg",
      "destaque": false,
      "criadoEm": "2026-05-30T02:40:24.000Z"
    },
    {
      "id": "p13",
      "nome": "Guirlanda Encanto em Crochê",
      "descricao": "Guirlanda de crochê feita à mão. Peça artesanal.",
      "preco": 59.9,
      "categoria": "Decoração",
      "imagem": "images/p13-guirlanda.jpg",
      "destaque": true,
      "criadoEm": "2026-05-30T02:40:24.000Z"
    },
    {
      "id": "p14",
      "nome": "Kit Maternidade Crochê",
      "descricao": "Kit maternidade em crochê artesanal, feito à mão com muito carinho.",
      "preco": 250,
      "categoria": "Crochê",
      "imagem": "images/p14-kit-maternidade.jpg",
      "destaque": true,
      "criadoEm": "2026-05-30T02:40:24.000Z"
    }
  ],
  "updatedAt": "2026-07-02T22:11:55.581Z"
}